{
    "id": [
        2,
        2,
        2,
        0,
        1,
        1,
        1,
        1,
        1,
        1,
        1,
        1,
        1,
        1,
        1,
        1,
        1,
        1,
        1,
        1,
        1,
        1,
        1,
        1,
        1,
        1,
        1,
        1,
        1,
        1,
        1,
        1,
        1,
        1,
        1,
        1,
        1,
        1,
        1,
        1,
        1,
        1,
        6,
        6,
        6,
        4,
        4,
        5,
        5
    ],
    "connections": [
        44,
        43
    ],
    "texte": [
        "Bonus Level",
        "Wenn du nur bisschen springen willst dann lass dich nach unten Fallen.",
        "Wenn du aber eine kleine Herausforderung magst, dann springe den Turm nach oben und finde da einen Weg."
    ],
    "poses": [
        {
            "x": -20.12649917602539,
            "y": -7.49943733215332,
            "z": 0.0
        },
        {
            "x": -17.316909790039064,
            "y": -7.440494537353516,
            "z": 0.0
        },
        {
            "x": -12.247859954833985,
            "y": -7.538731575012207,
            "z": 0.0
        },
        {
            "x": -22.669269561767579,
            "y": -7.145777702331543,
            "z": 0.0
        },
        {
            "x": 10.0088529586792,
            "y": 19.26479721069336,
            "z": 0.0
        },
        {
            "x": -4.022924423217773,
            "y": 21.26883888244629,
            "z": 0.0
        },
        {
            "x": 5.941823959350586,
            "y": 39.30336380004883,
            "z": 0.0
        },
        {
            "x": 8.987184524536133,
            "y": 51.28444290161133,
            "z": 0.0
        },
        {
            "x": 16.85749053955078,
            "y": -45.71529006958008,
            "z": 0.0
        },
        {
            "x": 18.87076187133789,
            "y": -45.71529006958008,
            "z": 0.0
        },
        {
            "x": 20.831050872802736,
            "y": -45.71529006958008,
            "z": 0.0
        },
        {
            "x": 22.844324111938478,
            "y": -45.71529006958008,
            "z": 0.0
        },
        {
            "x": 24.857593536376954,
            "y": -45.71529006958008,
            "z": 0.0
        },
        {
            "x": 26.764904022216798,
            "y": -45.71529006958008,
            "z": 0.0
        },
        {
            "x": 28.527454376220704,
            "y": -45.74028778076172,
            "z": 0.0
        },
        {
            "x": 30.391616821289064,
            "y": -45.71693801879883,
            "z": 0.0
        },
        {
            "x": 32.236358642578128,
            "y": -45.71693801879883,
            "z": 0.0
        },
        {
            "x": 34.034400939941409,
            "y": -45.763641357421878,
            "z": 0.0
        },
        {
            "x": 35.87914276123047,
            "y": -45.71693801879883,
            "z": 0.0
        },
        {
            "x": 37.793941497802737,
            "y": -45.71693801879883,
            "z": 0.0
        },
        {
            "x": 39.66203308105469,
            "y": -45.71693801879883,
            "z": 0.0
        },
        {
            "x": 41.55348205566406,
            "y": -45.69358825683594,
            "z": 0.0
        },
        {
            "x": 43.46827697753906,
            "y": -45.71693801879883,
            "z": 0.0
        },
        {
            "x": 45.266319274902347,
            "y": -45.763641357421878,
            "z": 0.0
        },
        {
            "x": 47.04100799560547,
            "y": -45.71693801879883,
            "z": 0.0
        },
        {
            "x": 48.89697265625,
            "y": -45.763641357421878,
            "z": 0.0
        },
        {
            "x": 50.76506805419922,
            "y": -45.71693801879883,
            "z": 0.0
        },
        {
            "x": 52.60980987548828,
            "y": -45.74028778076172,
            "z": 0.0
        },
        {
            "x": 54.45455551147461,
            "y": -45.74028778076172,
            "z": 0.0
        },
        {
            "x": 56.252593994140628,
            "y": -45.74028778076172,
            "z": 0.0
        },
        {
            "x": 21.971233367919923,
            "y": 58.79547882080078,
            "z": 0.0
        },
        {
            "x": 29.94658088684082,
            "y": 58.886627197265628,
            "z": 0.0
        },
        {
            "x": 37.96750259399414,
            "y": 58.93219757080078,
            "z": 0.0
        },
        {
            "x": 7.972306728363037,
            "y": 6.297301292419434,
            "z": 0.0
        },
        {
            "x": 18.05435562133789,
            "y": 57.25386047363281,
            "z": 0.0
        },
        {
            "x": 25.97480010986328,
            "y": 57.224952697753909,
            "z": 0.0
        },
        {
            "x": 33.98196792602539,
            "y": 57.25386047363281,
            "z": 0.0
        },
        {
            "x": 41.727149963378909,
            "y": 57.10310745239258,
            "z": 0.0
        },
        {
            "x": 48.98456573486328,
            "y": 57.28276824951172,
            "z": 0.0
        },
        {
            "x": 44.862632751464847,
            "y": 58.742984771728519,
            "z": 0.0
        },
        {
            "x": 45.989994049072269,
            "y": 58.742984771728519,
            "z": 0.0
        },
        {
            "x": -2.984919548034668,
            "y": 11.229540824890137,
            "z": 0.0
        },
        {
            "x": 11.50123119354248,
            "y": 60.01955032348633,
            "z": 0.0
        },
        {
            "x": 11.536821365356446,
            "y": 59.82379913330078,
            "z": 0.0
        },
        {
            "x": -2.493335485458374,
            "y": 118.06294250488281,
            "z": 0.0
        },
        {
            "x": 65.78557586669922,
            "y": -43.98895263671875,
            "z": 0.0
        },
        {
            "x": 53.96619415283203,
            "y": 58.01811981201172,
            "z": 0.0
        },
        {
            "x": -4.522040843963623,
            "y": 78.46134185791016,
            "z": 0.0
        },
        {
            "x": -4.518747329711914,
            "y": 118.4339370727539,
            "z": 0.0
        }
    ],
    "backgroundId": 0,
    "laserAimPoints": [
        {
            "x": 8.564952850341797,
            "y": 60.69578170776367
        },
        {
            "x": 11.536821365356446,
            "y": 58.293373107910159
        },
        {
            "x": -2.493335485458374,
            "y": 119.06294250488281
        }
    ],
    "doorsOpen": []
}